README.md
setup.cfg
setup.py
leaderelection/__init__.py
leaderelection/k8s.py
leaderelection/main.py
leaderelection.egg-info/PKG-INFO
leaderelection.egg-info/SOURCES.txt
leaderelection.egg-info/dependency_links.txt
leaderelection.egg-info/requires.txt
leaderelection.egg-info/top_level.txt